setup.cfg
setup.py
src/django_formsettesthelpers.egg-info/PKG-INFO
src/django_formsettesthelpers.egg-info/SOURCES.txt
src/django_formsettesthelpers.egg-info/dependency_links.txt
src/django_formsettesthelpers.egg-info/namespace_packages.txt
src/django_formsettesthelpers.egg-info/not-zip-safe
src/django_formsettesthelpers.egg-info/requires.txt
src/django_formsettesthelpers.egg-info/top_level.txt
src/formsettesthelpers/__init__.py
src/formsettesthelpers/formset.py
src/formsettesthelpers/tests.py
src/formsettesthelpers/test_app/__init__.py
src/formsettesthelpers/test_app/forms.py
src/formsettesthelpers/test_app/settings.py
src/formsettesthelpers/test_app/urls.py
src/formsettesthelpers/test_app/views.py