Metadata-Version: 1.1
Name: django-formsettesthelpers
Version: 0.1
Summary: Django test helpers for generating formset data.
Home-page: https://github.com/Raekkeri/django-formsettesthelpers
Author: Teemu Husso
Author-email: teemu.husso@gmail.com
License: UNKNOWN
Download-URL: https://github.com/raekkeri/django-formsettesthelpers/tarball/0.1
Keywords: django,formset,test,helpers
Platform: UNKNOWN
